oxapay_python/__init__.py
oxapay_python/exceptions.py
oxapay_python/manager.py
oxapay_python/endpoints/__init__.py
oxapay_python/endpoints/_mixins.py
oxapay_python/endpoints/account.py
oxapay_python/endpoints/common.py
oxapay_python/endpoints/exchange.py
oxapay_python/endpoints/payment.py
oxapay_python/endpoints/payout.py
oxapay_python/http/__init__.py
oxapay_python/http/client.py
oxapay_python/services/__init__.py
oxapay_python/services/webhook.py
oxapay_python-1.1.0.dist-info/METADATA
oxapay_python-1.1.0.dist-info/WHEEL
oxapay_python-1.1.0.dist-info/licenses/LICENSE
oxapay_python-1.1.0.dist-info/RECORD
