Metadata-Version: 2.4
Name: oxapay-python
Version: 1.1.0
Summary: Official Python SDK for OxaPay — accept crypto payments, exchanges, and payouts.
Project-URL: Homepage, https://oxapay.com
Project-URL: Documentation, https://docs.oxapay.com
Project-URL: Source, https://github.com/OxaPay/oxapay-python
Project-URL: Issues, https://github.com/OxaPay/oxapay-python/issues
Author: OxaPay
License: Apache License 2.0
License-File: LICENSE
Keywords: crypto,exchange,oxapay,payment,payout,sdk
Requires-Python: >=3.8
Requires-Dist: requests>=2.31.0
Provides-Extra: dev
Requires-Dist: pytest>=7.4; extra == 'dev'
Requires-Dist: responses>=0.25.0; extra == 'dev'
Requires-Dist: ruff>=0.6.0; extra == 'dev'
